src/__init__.py
src/neon_connector.py
neon_connector-0.1.1.dist-info/METADATA
neon_connector-0.1.1.dist-info/WHEEL
neon_connector-0.1.1.dist-info/top_level.txt
neon_connector-0.1.1.dist-info/RECORD
