Metadata-Version: 2.1
Name: neon-connector
Version: 0.1.1
Summary: Connect to Neon DB and perform operations through Python.
Home-page: https://github.com/supertypeai/neon_connector
Author: Timotius Marselo
Author-email: timotiusmarselo@gmail.com
Classifier: Programming Language :: Python :: 3
Classifier: License :: OSI Approved :: MIT License
Classifier: Operating System :: OS Independent
Requires-Python: >=3.6
Requires-Dist: python-dotenv ==1.0.0
Requires-Dist: psycopg2 ==2.9.9
Requires-Dist: pandas ==2.2.1
